pdstools/__init__.py
pdstools/cli.py
pdstools/py.typed
pdstools/adm/ADMDatamart.py
pdstools/adm/ADMTrees.py
pdstools/adm/Aggregates.py
pdstools/adm/BinAggregator.py
pdstools/adm/Plots.py
pdstools/adm/Reports.py
pdstools/adm/Schema.py
pdstools/adm/__init__.py
pdstools/app/__init__.py
pdstools/app/decision_analyzer/Home.py
pdstools/app/decision_analyzer/__init__.py
pdstools/app/decision_analyzer/da_streamlit_utils.py
pdstools/app/decision_analyzer/pages/10_Arbitration_Component_Distribution.py
pdstools/app/decision_analyzer/pages/11_Business_Lever_Analysis.py
pdstools/app/decision_analyzer/pages/1_Global_Filters.py
pdstools/app/decision_analyzer/pages/2_Global_Dashboard.py
pdstools/app/decision_analyzer/pages/3_Action_Distribution.py
pdstools/app/decision_analyzer/pages/4_Action_Funnel.py
pdstools/app/decision_analyzer/pages/5_Global_Sensitivity.py
pdstools/app/decision_analyzer/pages/6_Win_Loss_Analysis.py
pdstools/app/decision_analyzer/pages/7_Personalization_Analysis.py
pdstools/app/decision_analyzer/pages/__init__.py
pdstools/app/decision_analyzer/pages/unfinished_pages/8_Offer_Quality_Analysis.py
pdstools/app/decision_analyzer/pages/unfinished_pages/9_Thresholding_Analysis.py
pdstools/app/health_check/Home.py
pdstools/app/health_check/__init__.py
pdstools/app/health_check/pages/1_Data_Import.py
pdstools/app/health_check/pages/2_Data_Filters.py
pdstools/app/health_check/pages/3_Reports.py
pdstools/app/health_check/pages/__init__.py
pdstools/decision_analyzer/__init__.py
pdstools/decision_analyzer/data_read_utils.py
pdstools/decision_analyzer/decision_data.py
pdstools/decision_analyzer/plots.py
pdstools/decision_analyzer/table_definition.py
pdstools/decision_analyzer/utils.py
pdstools/explanations/Aggregate.py
pdstools/explanations/Explanations.py
pdstools/explanations/ExplanationsUtils.py
pdstools/explanations/FilterWidget.py
pdstools/explanations/Plots.py
pdstools/explanations/Preprocess.py
pdstools/explanations/Reports.py
pdstools/explanations/__init__.py
pdstools-4.5.0.dist-info/licenses/LICENSE
pdstools-4.5.0.dist-info/METADATA
pdstools-4.5.0.dist-info/WHEEL
pdstools-4.5.0.dist-info/entry_points.txt
pdstools-4.5.0.dist-info/top_level.txt
pdstools-4.5.0.dist-info/RECORD
