Metadata-Version: 2.4
Name: pdstools
Version: 4.5.0
Summary: Open source tooling that helps Data Scientists to analyze Pega models and conduct impactful analyses.
Author-email: Stijn Kas <stijn.kas@pega.com>
License: Apache-2.0
Project-URL: Homepage, https://github.com/pegasystems/pega-datascientist-tools
Project-URL: Bug Tracker, https://github.com/pegasystems/pega-datascientist-tools/issues
Project-URL: Docs, https://pegasystems.github.io/pega-datascientist-tools/
Keywords: pega,pegasystems,pdstools,datascientist,tools
Classifier: License :: OSI Approved :: Apache Software License
Classifier: Development Status :: 4 - Beta
Classifier: Intended Audience :: Developers
Classifier: Programming Language :: Python :: 3
Requires-Python: <3.14,>=3.9
License-File: LICENSE
Requires-Dist: polars!=1.35.1,<=1.36.1,>=1.30
Requires-Dist: typing_extensions
Provides-Extra: adm
Requires-Dist: plotly[express]>=6.0; extra == "adm"
Requires-Dist: requests; extra == "adm"
Provides-Extra: pega-io
Requires-Dist: aioboto3; extra == "pega-io"
Requires-Dist: polars_hash; extra == "pega-io"
Provides-Extra: api
Requires-Dist: httpx; extra == "api"
Requires-Dist: pydantic; extra == "api"
Requires-Dist: anyio; extra == "api"
Provides-Extra: healthcheck
Requires-Dist: pdstools[adm]; extra == "healthcheck"
Requires-Dist: great_tables>=0.13; extra == "healthcheck"
Requires-Dist: quarto; extra == "healthcheck"
Requires-Dist: papermill; extra == "healthcheck"
Requires-Dist: xlsxwriter>=3.0; extra == "healthcheck"
Requires-Dist: pydot; extra == "healthcheck"
Provides-Extra: explanations
Requires-Dist: duckdb; extra == "explanations"
Requires-Dist: plotly[express]; extra == "explanations"
Requires-Dist: pyarrow; extra == "explanations"
Requires-Dist: pyyaml; extra == "explanations"
Requires-Dist: ipywidgets; extra == "explanations"
Provides-Extra: app
Requires-Dist: pdstools[healthcheck]; extra == "app"
Requires-Dist: streamlit>=1.45; extra == "app"
Provides-Extra: onnx
Requires-Dist: scikit-learn>=1.6.1; extra == "onnx"
Requires-Dist: skl2onnx>=1.19.1; extra == "onnx"
Requires-Dist: onnx<1.20,>=1.18; extra == "onnx"
Requires-Dist: pdstools[api]; extra == "onnx"
Requires-Dist: onnxruntime==1.18.1; python_full_version < "3.10" and extra == "onnx"
Requires-Dist: onnxruntime>=1.22; python_full_version >= "3.10" and extra == "onnx"
Requires-Dist: scipy>=1.15.3; python_full_version >= "3.10" and extra == "onnx"
Provides-Extra: all
Requires-Dist: pdstools[app,explanations,onnx,pega_io]; extra == "all"
Provides-Extra: dev
Requires-Dist: pre-commit; extra == "dev"
Provides-Extra: docs
Requires-Dist: sphinx; extra == "docs"
Requires-Dist: furo; extra == "docs"
Requires-Dist: sphinx-autoapi; extra == "docs"
Requires-Dist: nbsphinx; extra == "docs"
Requires-Dist: sphinx-copybutton; extra == "docs"
Requires-Dist: sphinx-tabs; extra == "docs"
Requires-Dist: myst-parser; extra == "docs"
Requires-Dist: sphinx-argparse; extra == "docs"
Requires-Dist: xgboost; extra == "docs"
Requires-Dist: pydantic; extra == "docs"
Requires-Dist: httpx; extra == "docs"
Requires-Dist: streamlit; extra == "docs"
Requires-Dist: duckdb; extra == "docs"
Requires-Dist: anyio; extra == "docs"
Provides-Extra: tests
Requires-Dist: testbook; extra == "tests"
Requires-Dist: pytest; extra == "tests"
Requires-Dist: pytest-cov; extra == "tests"
Requires-Dist: pytest-httpx; extra == "tests"
Requires-Dist: pytest-mock; extra == "tests"
Requires-Dist: pytest-asyncio; extra == "tests"
Requires-Dist: moto; extra == "tests"
Requires-Dist: openpyxl; extra == "tests"
Requires-Dist: pdstools[all]; extra == "tests"
Requires-Dist: coverage; extra == "tests"
Requires-Dist: itables; extra == "tests"
Dynamic: license-file
